cli_SQL-0.1.data/data/src/SQLcli.py/SQLcli.py
src/SQLcli.py
src/__init__.py
cli_SQL-0.1.dist-info/LICENCE
cli_SQL-0.1.dist-info/METADATA
cli_SQL-0.1.dist-info/WHEEL
cli_SQL-0.1.dist-info/top_level.txt
cli_SQL-0.1.dist-info/RECORD
